mkdocs_cu_ab6459/__init__.py
mkdocs_cu_ab6459/main.html
mkdocs_cu_ab6459/mkdocs_theme.yml
mkdocs_cu_ab6459/css/bootstrap-grid.css
mkdocs_cu_ab6459/css/bootstrap-grid.min.css
mkdocs_cu_ab6459/css/bootstrap-grid.rtl.css
mkdocs_cu_ab6459/css/bootstrap-grid.rtl.min.css
mkdocs_cu_ab6459/css/bootstrap-reboot.css
mkdocs_cu_ab6459/css/bootstrap-reboot.min.css
mkdocs_cu_ab6459/css/bootstrap-reboot.rtl.css
mkdocs_cu_ab6459/css/bootstrap-reboot.rtl.min.css
mkdocs_cu_ab6459/css/bootstrap-utilities.css
mkdocs_cu_ab6459/css/bootstrap-utilities.min.css
mkdocs_cu_ab6459/css/bootstrap-utilities.rtl.css
mkdocs_cu_ab6459/css/bootstrap-utilities.rtl.min.css
mkdocs_cu_ab6459/css/bootstrap.css
mkdocs_cu_ab6459/css/bootstrap.min.css
mkdocs_cu_ab6459/css/bootstrap.rtl.css
mkdocs_cu_ab6459/css/bootstrap.rtl.min.css
mkdocs_cu_ab6459/css/custom.css
mkdocs_cu_ab6459/css/diagram.css
mkdocs_cu_ab6459/css/prism.css
mkdocs_cu_ab6459/images/logo_dark.png
mkdocs_cu_ab6459/images/logo_light.png
mkdocs_cu_ab6459/images/logo_white.png
mkdocs_cu_ab6459/js/bootstrap.bundle.js
mkdocs_cu_ab6459/js/bootstrap.bundle.min.js
mkdocs_cu_ab6459/js/bootstrap.esm.js
mkdocs_cu_ab6459/js/bootstrap.esm.min.js
mkdocs_cu_ab6459/js/bootstrap.js
mkdocs_cu_ab6459/js/bootstrap.min.js
mkdocs_cu_ab6459/js/darkmode.js
mkdocs_cu_ab6459/js/prism.js
mkdocs_cu_ab6459/js/simple-diagram.js
mkdocs_cu_ab6459-0.1.9.8.dist-info/METADATA
mkdocs_cu_ab6459-0.1.9.8.dist-info/WHEEL
mkdocs_cu_ab6459-0.1.9.8.dist-info/entry_points.txt
mkdocs_cu_ab6459-0.1.9.8.dist-info/top_level.txt
mkdocs_cu_ab6459-0.1.9.8.dist-info/RECORD
