Metadata-Version: 2.1
Name: mkdocs_cu_ab6459
Version: 0.1.9.8
Summary: Improved and extended version of the Windmill theme
Home-page: https://github.coventry.ac.uk/ab6459/mkdocs_cu_ab6459
Author: Ian Cornelius
Author-email: ab6459@coventry.ac.uk
License: MIT
Classifier: License :: OSI Approved :: MIT License
Classifier: Topic :: Documentation
Classifier: Topic :: Text Processing
Requires-Dist: mkdocs
